metamove/__init__.py
metamove/cli.py
metamove/main.py
metamove/yaml_transformer.py
metamove-0.4.0.dist-info/METADATA
metamove-0.4.0.dist-info/WHEEL
metamove-0.4.0.dist-info/entry_points.txt
metamove-0.4.0.dist-info/RECORD
