Metadata-Version: 2.3
Name: metamove
Version: 0.4.0
Summary: Transform YAML: move meta under config.meta
License: MIT
Keywords: yaml,transform,cli
Author: Oliver Laslett
Author-email: oliver@lightdash.com
Requires-Python: >=3.9,<3.14
Classifier: Development Status :: 4 - Beta
Classifier: Environment :: Console
Classifier: Intended Audience :: Developers
Classifier: License :: OSI Approved :: MIT License
Classifier: Programming Language :: Python :: 3
Classifier: Programming Language :: Python :: 3.9
Classifier: Programming Language :: Python :: 3.10
Classifier: Programming Language :: Python :: 3.11
Classifier: Programming Language :: Python :: 3.12
Classifier: Programming Language :: Python :: 3.13
Classifier: Programming Language :: Python :: 3.8
Requires-Dist: click (>=8.0.0,<9.0.0)
Requires-Dist: ruamel-yaml (==0.18.6)
Requires-Dist: setuptools (>=78.1.1,<79.0.0)
Project-URL: Repository, https://github.com/lightdash/metamove
